concise_concepts/__init__.py
concise_concepts/conceptualizer/Conceptualizer.py
concise_concepts/conceptualizer/__init__.py
concise_concepts/examples/__init__.py
concise_concepts/examples/data.py
concise_concepts/examples/example_gensim_custom_model.py
concise_concepts/examples/example_gensim_custom_path.py
concise_concepts/examples/example_gensim_default.py
concise_concepts/examples/example_spacy.py
concise_concepts-0.8.1.dist-info/entry_points.txt
concise_concepts-0.8.1.dist-info/LICENSE
concise_concepts-0.8.1.dist-info/WHEEL
concise_concepts-0.8.1.dist-info/METADATA
concise_concepts-0.8.1.dist-info/RECORD
