Metadata-Version: 2.1
Name: concise-concepts
Version: 0.8.1
Summary: This repository contains an easy and intuitive approach to few-shot NER using most similar expansion over spaCy embeddings. Now with entity confidence scores!
Home-page: https://github.com/pandora-intelligence/concise-concepts
License: MIT
Keywords: spacy,NER,few-shot classification,nlu
Author: David Berenstein
Author-email: david.m.berenstein@gmail.com
Requires-Python: >=3.8,<3.12
Classifier: Intended Audience :: Developers
Classifier: Intended Audience :: Science/Research
Classifier: License :: OSI Approved :: MIT License
Classifier: Operating System :: OS Independent
Classifier: Programming Language :: Python :: 3
Classifier: Programming Language :: Python :: 3.8
Classifier: Programming Language :: Python :: 3.9
Classifier: Programming Language :: Python :: 3.10
Classifier: Programming Language :: Python :: 3.10
Classifier: Programming Language :: Python :: 3.11
Classifier: Programming Language :: Python :: 3.8
Classifier: Programming Language :: Python :: 3.9
Classifier: Topic :: Scientific/Engineering
Classifier: Topic :: Software Development
Requires-Dist: gensim (>=4,<5)
Requires-Dist: scipy (>=1.7,<2.0)
Requires-Dist: sense2vec (>=2.0.1,<3.0.0)
Requires-Dist: spacy (>=3,<4)
Requires-Dist: spaczz (>=0.5.4,<0.6.0)
Project-URL: Documentation, https://github.com/pandora-intelligence/concise-concepts
Project-URL: Repository, https://github.com/pandora-intelligence/concise-concepts
